PyTestLog2DB/PyTestLog2DB.pdf
PyTestLog2DB/__init__.py
PyTestLog2DB/__main__.py
PyTestLog2DB/pytestlog2db.py
PyTestLog2DB/version.py
PyTestLog2DB/xsd/junit.xsd
PyTestLog2DB-0.3.4.dist-info/LICENSE
PyTestLog2DB-0.3.4.dist-info/METADATA
PyTestLog2DB-0.3.4.dist-info/WHEEL
PyTestLog2DB-0.3.4.dist-info/top_level.txt
PyTestLog2DB-0.3.4.dist-info/RECORD
