Metadata-Version: 2.1
Name: PyTestLog2DB
Version: 0.3.4
Summary: Imports pytest result(s) to TestResultWebApp database
Home-page: https://github.com/test-fullautomation/python-pytestlog2db
Author: Tran Duy Ngoan
Author-email: Ngoan.TranDuy@vn.bosch.com
License: UNKNOWN
Platform: UNKNOWN
Classifier: Programming Language :: Python :: 3
Classifier: License :: OSI Approved :: Apache Software License
Classifier: Operating System :: OS Independent
Classifier: Development Status :: 4 - Beta
Classifier: Intended Audience :: Developers
Classifier: Topic :: Software Development
Requires-Python: >=3.0
License-File: LICENSE
Requires-Dist: colorama
Requires-Dist: TestResultDBAccess
Requires-Dist: lxml
